plotmark/__init__.py
plotmark/mark.py
plotmark-1.0.0.dist-info/LICENSE
plotmark-1.0.0.dist-info/METADATA
plotmark-1.0.0.dist-info/WHEEL
plotmark-1.0.0.dist-info/top_level.txt
plotmark-1.0.0.dist-info/RECORD
