Metadata-Version: 2.1
Name: plotmark
Version: 1.0.0
Summary: Plot markers for Matplotlib
Home-page: https://github.com/tbennun/plotmark
Author: Tal Ben-Nun
Author-email: tbennun@gmail.com
License: UNKNOWN
Platform: UNKNOWN
Requires-Dist: matplotlib
